dataframe_faker/__init__.py
dataframe_faker/constraints.py
dataframe_faker/dataframe.py
dataframe_faker/py.typed
dataframe_faker-0.1.3.dist-info/METADATA
dataframe_faker-0.1.3.dist-info/WHEEL
dataframe_faker-0.1.3.dist-info/licenses/LICENSE
dataframe_faker-0.1.3.dist-info/RECORD
