Metadata-Version: 2.4
Name: dataframe-faker
Version: 0.1.3
Summary: A simple helper for generating DataFrames filled with fake data with the help of Faker.
Project-URL: Repository, https://github.com/VillePuuska/dataframe-faker
Author-email: Ville Puuska <puuskaville@gmail.com>
License-File: LICENSE
Classifier: Programming Language :: Python :: 3.11
Classifier: Programming Language :: Python :: 3.12
Requires-Python: >=3.11
Requires-Dist: faker>=36.1.1
Provides-Extra: pyspark
Requires-Dist: pyspark>=3.5.0; extra == 'pyspark'
